pydparser/__init__.py
pydparser/constants.py
pydparser/create_jd_corpus.py
pydparser/create_spacy_corpus.py
pydparser/job_parser.py
pydparser/matching.py
pydparser/resume_parser.py
pydparser/skills.csv
pydparser/utils.py
pydparser/data/jd/test.spacy
pydparser/data/jd/train.spacy
pydparser/data/jd/validation.spacy
pydparser/data/resumes/dev.spacy
pydparser/data/resumes/train.spacy
pydparser/models/jd_model/config.cfg
pydparser/models/jd_model/meta.json
pydparser/models/jd_model/tokenizer
pydparser/models/jd_model/tagger/cfg
pydparser/models/jd_model/tagger/model
pydparser/models/jd_model/tok2vec/cfg
pydparser/models/jd_model/tok2vec/model
pydparser/models/jd_model/vocab/key2row
pydparser/models/jd_model/vocab/strings.json
pydparser/models/jd_model/vocab/vectors
pydparser/models/jd_model/vocab/vectors.cfg
pydparser/models/res_model/config.cfg
pydparser/models/res_model/meta.json
pydparser/models/res_model/tokenizer
pydparser/models/res_model/ner/cfg
pydparser/models/res_model/ner/model
pydparser/models/res_model/ner/moves
pydparser/models/res_model/tok2vec/cfg
pydparser/models/res_model/tok2vec/model
pydparser/models/res_model/vocab/key2row
pydparser/models/res_model/vocab/strings.json
pydparser/models/res_model/vocab/vectors
pydparser/models/res_model/vocab/vectors.cfg
tests/utils_tests.py
venv/bin/activate_this.py
venv/bin/dumppdf.py
venv/bin/pdf2txt.py
venv/bin/plac_runner.py
venv/bin/rst2html.py
venv/bin/rst2html4.py
venv/bin/rst2html5.py
venv/bin/rst2latex.py
venv/bin/rst2man.py
venv/bin/rst2odt.py
venv/bin/rst2odt_prepstyles.py
venv/bin/rst2pseudoxml.py
venv/bin/rst2s5.py
venv/bin/rst2xetex.py
venv/bin/rst2xml.py
venv/bin/rstpep2html.py
pydparser-1.0.4.dist-info/LICENSE
pydparser-1.0.4.dist-info/METADATA
pydparser-1.0.4.dist-info/WHEEL
pydparser-1.0.4.dist-info/top_level.txt
pydparser-1.0.4.dist-info/RECORD
