Metadata-Version: 2.1
Name: pydparser
Version: 1.0.4
Summary: A simple resume and job description parser used for extracting information from resumes and job descriptions and compatible with python 3.10 upwords
Home-page: https://github.com/justicea83/pydparser
Author: justicea83
License: MIT
Keywords: python,resume,jd,job description,parser
Classifier: License :: OSI Approved :: MIT License
Classifier: Programming Language :: Python :: 3.10
Classifier: Operating System :: OS Independent
Requires-Python: >=3.10
License-File: LICENSE
Requires-Dist: spacy ==3.7.2
Requires-Dist: jsonschema ==4.20.0
Requires-Dist: scikit-learn ==1.3.2
Requires-Dist: tqdm ==4.66.1
Requires-Dist: nltk ==3.8.1
Requires-Dist: pandas ==2.1.4
Requires-Dist: docx2txt ==0.8
Requires-Dist: python-dateutil ==2.8.2
Requires-Dist: pdfminer.six ==20221105
Requires-Dist: plac ==1.4.2
Requires-Dist: datasets ==2.16.0
